shellcode/__init__.py
shellcode/__main__.py
shellcode-0.2.1.dist-info/entry_points.txt
shellcode-0.2.1.dist-info/WHEEL
shellcode-0.2.1.dist-info/METADATA
shellcode-0.2.1.dist-info/RECORD
